{"dct_title_s": "Bublr Bike Stations Milwaukee County, Wisconsin March 2018","dct_description_sm": ["This point layer represents Bublr Bikeshare Stations for Milwaukee County, Wisconsin in 2018. The data was obtained from Bublr as an excel worksheet with addresses, latitude and longitude, and stall count information. A shapefile was created by American Geogrphical Society Library Staff."],"dct_language_sm": ["eng"],"dct_creator_sm": ["James Davies (Senior Director of Operations and Planning, Bublr Bikes)"],"schema_provider_s": "American Geographical Society Library","gbl_resourceClass_sm": ["Datasets"],"gbl_resourceType_sm": ["Point data"],"dcat_theme_sm": ["Transportation"],"dct_temporal_sm": ["2018-03-08"],"dct_issued_s": "2018","gbl_indexYear_im": [2018],"dct_spatial_sm": ["Milwaukee County","Wisconsin"],"locn_geometry": "ENVELOPE(-87.8773, -88.03359, 43.098, 43.00475)","dcat_bbox": "ENVELOPE(-88.03359, -87.8773, 43.098, 43.00475)","dct_rights_sm": ["Although this data is being distributed by the American Geographical Society Library at the University of Wisconsin-Milwaukee Libraries, no warranty expressed or implied is made by the University as to the accuracy of the data and related materials. The act of distribution shall not constitute any such warranty, and no responsibility is assumed by the University in the use of this data, or related materials."],"dct_accessRights_s": "Public","dct_format_s": "Shapefile","gbl_wxsIdentifier_s": "27DCB7B4-AA71-4034-A0EA-5CF697C361E0","dct_references_s": "{\"http://schema.org/url\":\"\",\"http://schema.org/downloadUrl\":\"\",\"http://www.isotc211.org/schemas/2005/gmd\":\"https://geodata.uwm.edu/metadata/MilwaukeeCounty_BublrBikeStations_2018.shp_ISO.xml\"}","id": "27DCB7B4-AA71-4034-A0EA-5CF697C361E0","gbl_mdModified_dt": "2023-09-11T20:10:01.5296456Z","gbl_mdVersion_s": "Aardvark","gbl_suppressed_b": false}